more_context/__init__.py
more_context/safe_context_manager.py
more_context-0.0.1.dist-info/WHEEL
more_context-0.0.1.dist-info/METADATA
more_context-0.0.1.dist-info/RECORD
